LICENSE
README.md
pyproject.toml
setup.py
meta_msg/__init__.py
meta_msg/exceptions.py
meta_msg/meta_msg.py
meta_msg.egg-info/PKG-INFO
meta_msg.egg-info/SOURCES.txt
meta_msg.egg-info/dependency_links.txt
meta_msg.egg-info/top_level.txt
meta_msg/status_codes/__init__.py
meta_msg/status_codes/grpc.py
meta_msg/status_codes/http.py
scripts/__init__.py
scripts/poetry.py
tests/__init__.py
tests/test.py